dbus_cffi.pyd
http_cffi.pyd
json_cffi.pyd
gruvi/compat.py
gruvi/dbus.py
gruvi/dbus_ffi.py
gruvi/error.py
gruvi/fibers.py
gruvi/futures.py
gruvi/http.py
gruvi/http_ffi.py
gruvi/hub.py
gruvi/jsonrpc.py
gruvi/jsonrpc_ffi.py
gruvi/local.py
gruvi/logging.py
gruvi/protocols.py
gruvi/pyuv.py
gruvi/reader.py
gruvi/socketpair.py
gruvi/ssl.py
gruvi/stream.py
gruvi/sync.py
gruvi/util.py
gruvi/_version.py
gruvi/__init__.py
gruvi/txdbus/error.py
gruvi/txdbus/marshal.py
gruvi/txdbus/message.py
gruvi/txdbus/__init__.py
gruvi-0.9.2.dist-info/DESCRIPTION.rst
gruvi-0.9.2.dist-info/METADATA
gruvi-0.9.2.dist-info/pydist.json
gruvi-0.9.2.dist-info/RECORD
gruvi-0.9.2.dist-info/top_level.txt
gruvi-0.9.2.dist-info/WHEEL
