Metadata-Version: 2.0
Name: gruvi
Version: 0.9.2
Summary: Synchronous evented IO with pyuv and fibers
Home-page: https://github.com/geertj/gruvi
Author: Geert Jansen
Author-email: geertj@gmail.com
License: MIT
Platform: UNKNOWN
Classifier: Development Status :: 4 - Beta
Classifier: License :: OSI Approved :: MIT License
Classifier: Operating System :: POSIX
Classifier: Operating System :: Microsoft :: Windows
Classifier: Operating System :: MacOS :: MacOS X
Classifier: Programming Language :: Python :: 2.6
Classifier: Programming Language :: Python :: 2.7
Classifier: Programming Language :: Python :: 3.3
Requires-Dist: pycparser
Requires-Dist: cffi
Requires-Dist: fibers
Requires-Dist: pyuv
